Metadata-Version: 2.1
Name: ctpy
Version: 0.0.1
Summary: chemicaltagger for python
Home-page: UNKNOWN
Author: zbc
Author-email: zbc@mail.ustc.edu.cn
License: UNKNOWN
Platform: UNKNOWN
Classifier: Programming Language :: Python :: 3
Classifier: License :: OSI Approved :: MIT License
Classifier: Operating System :: OS Independent
